foliant/preprocessors/glossary.py
foliantcontrib.glossary-1.0.0.dist-info/LICENSE
foliantcontrib.glossary-1.0.0.dist-info/METADATA
foliantcontrib.glossary-1.0.0.dist-info/WHEEL
foliantcontrib.glossary-1.0.0.dist-info/top_level.txt
foliantcontrib.glossary-1.0.0.dist-info/RECORD
