Metadata-Version: 2.1
Name: foliantcontrib.glossary
Version: 1.0.0
Summary: Preprocessor for Foliant for collecting document glossary.
Home-page: https://github.com/foliant-docs/foliantcontrib.glossary
Author: Anton Bukhtiyarov
Author-email: apkraft@gmail.com
License: MIT
Platform: any
Classifier: Development Status :: 5 - Production/Stable
Classifier: Environment :: Console
Classifier: Intended Audience :: Developers
Classifier: License :: OSI Approved :: MIT License
Classifier: Operating System :: OS Independent
Classifier: Programming Language :: Python
Classifier: Topic :: Documentation
Classifier: Topic :: Utilities
Requires-Dist: foliant (>=1.0.10)
Requires-Dist: foliantcontrib.includes (>=1.1.6)
